game_engine/__init__.py
game_engine/gui.py
game_engine/main.py
game_engine/objects.py
game_engine/world.py
game_engine-0.1.6.dist-info/METADATA
game_engine-0.1.6.dist-info/WHEEL
game_engine-0.1.6.dist-info/entry_points.txt
game_engine-0.1.6.dist-info/top_level.txt
game_engine-0.1.6.dist-info/RECORD
