Metadata-Version: 2.4
Name: game-engine
Version: 0.1.6
Summary: Simple 3D FPS Demo Engine with PyQt6 and procedural world
Author-email: Antonin Siska <siska.antonin.mail@gmail.com>
License: MIT License
Project-URL: Homepage, https://github.com/antoninsiska/game-engine
Project-URL: Repository, https://github.com/antoninsiska/game-engine
Project-URL: BugTracker, https://github.com/antoninsiska/game-engine/issues
Classifier: License :: OSI Approved :: MIT License
Classifier: Programming Language :: Python :: 3
Classifier: Programming Language :: Python :: 3 :: Only
Classifier: Programming Language :: Python :: 3.9
Classifier: Programming Language :: Python :: 3.10
Classifier: Programming Language :: Python :: 3.11
Requires-Python: >=3.9
Requires-Dist: PyQt6>=6.4
